src/__init__.py
src/conjugator.py
conjugate-0.0.1.1.dist-info/LICENSE
conjugate-0.0.1.1.dist-info/METADATA
conjugate-0.0.1.1.dist-info/WHEEL
conjugate-0.0.1.1.dist-info/top_level.txt
conjugate-0.0.1.1.dist-info/RECORD
